spotify_webapi/__init__.py
spotify_webapi-1.0.3.dist-info/LICENSE
spotify_webapi-1.0.3.dist-info/METADATA
spotify_webapi-1.0.3.dist-info/WHEEL
spotify_webapi-1.0.3.dist-info/top_level.txt
spotify_webapi-1.0.3.dist-info/RECORD
