Metadata-Version: 2.1
Name: spotify-webapi
Version: 1.0.3
Summary: get tracks of spotify playlists without using the official api
Home-page: https://github.com/ruru4143/spotify-webapi
Author: ruru4143
Author-email: pypi@ruru.pw
License: GPLv3
Download-URL: https://github.com/ruru4143/spotify-webapi1.0.3
Keywords: spotify,track,scaping,webapi,webscraper,song,scraper
Platform: UNKNOWN
Classifier: Intended Audience :: Developers
Classifier: License :: OSI Approved :: GNU General Public License v3 (GPLv3)
Classifier: Programming Language :: Python
Classifier: Programming Language :: Python :: 3
Classifier: Programming Language :: Python :: 2.7
Classifier: Programming Language :: Python :: 3.5
Classifier: Programming Language :: Python :: 3.6
Classifier: Programming Language :: Python :: 3.7
Classifier: Natural Language :: English
Requires-Dist: beautifulsoup4
